unionizer/__init__.py
unionizer/help.py
unionizer/_core/__init__.py
unionizer/_core/_assign_core.py
unionizer/_core/_bond_core.py
unionizer-1.8.5.dist-info/METADATA
unionizer-1.8.5.dist-info/WHEEL
unionizer-1.8.5.dist-info/top_level.txt
unionizer-1.8.5.dist-info/RECORD
