Metadata-Version: 2.1
Name: unionizer
Version: 1.8.5
Summary: Unionizer helps developers pair objects together.
Home-page: https://github.com
Author: unionizer
Author-email: toolkitr.email@gmail.com
License: MIT
Keywords: unionizer,union,unions
Classifier: Development Status :: 1 - Planning
Classifier: Development Status :: 2 - Pre-Alpha
Classifier: Development Status :: 3 - Alpha
Classifier: Development Status :: 4 - Beta
Classifier: Intended Audience :: Developers
Classifier: Topic :: Software Development :: Build Tools
Classifier: License :: OSI Approved :: MIT License
Classifier: Programming Language :: Python :: 3
Classifier: Programming Language :: Python :: 3.7
